fast_enum/__init__.py
fast_enum/fastenum.py
fastenumplus-1.4.0.dist-info/LICENSE
fastenumplus-1.4.0.dist-info/METADATA
fastenumplus-1.4.0.dist-info/WHEEL
fastenumplus-1.4.0.dist-info/top_level.txt
fastenumplus-1.4.0.dist-info/RECORD
